jupyverse/__init__.py
jupyverse/py.typed
jupyverse-0.11.3.dist-info/licenses/COPYING.md
jupyverse-0.11.3.dist-info/WHEEL
jupyverse-0.11.3.dist-info/METADATA
jupyverse-0.11.3.dist-info/RECORD
