Metadata-Version: 2.4
Name: jupyverse
Version: 0.11.3
Summary: A set of FPS plugins implementing a Jupyter server
Keywords: jupyter,server,fastapi,plugins
Author: Jupyter Development Team
Author-email: Jupyter Development Team <jupyter@googlegroups.com>
License-Expression: BSD-3-Clause
License-File: COPYING.md
Classifier: Development Status :: 5 - Production/Stable
Classifier: Intended Audience :: Developers
Classifier: License :: OSI Approved :: BSD License
Classifier: Programming Language :: Python
Classifier: Programming Language :: Python :: 3.10
Classifier: Programming Language :: Python :: 3.11
Classifier: Programming Language :: Python :: 3.12
Classifier: Programming Language :: Python :: 3.13
Classifier: Programming Language :: Python :: 3.14
Classifier: Programming Language :: Python :: Implementation :: CPython
Classifier: Programming Language :: Python :: Implementation :: PyPy
Requires-Dist: fps[click,fastapi,anycorn]>=0.5.9,<0.6.0
Requires-Dist: fps-contents>=0.10.3,<0.11.0
Requires-Dist: fps-file-id>=0.3.4,<0.4.0
Requires-Dist: fps-file-watcher>=0.1.3,<0.2.0
Requires-Dist: fps-kernel-subprocess>=0.1.5,<0.2.0
Requires-Dist: fps-kernels>=0.10.5,<0.11.0
Requires-Dist: fps-terminals>=0.9.3,<0.10.0
Requires-Dist: fps-nbconvert>=0.9.3,<0.10.0
Requires-Dist: fps-yjs>=0.11.3,<0.12.0
Requires-Dist: fps-lab>=0.10.2,<0.11.0
Requires-Dist: fps-frontend>=0.9.3,<0.10.0
Requires-Dist: jupyverse-api>=0.13.1,<0.14.0
Requires-Dist: rich-click>=1.6.1,<2
Requires-Dist: eval-type-backport ; python_full_version < '3.10'
Requires-Dist: fps-auth>=0.9.3,<0.10.0 ; extra == 'auth'
Requires-Dist: fps-login>=0.9.3,<0.10.0 ; extra == 'auth'
Requires-Dist: fps-auth-fief>=0.9.4,<0.10.0 ; extra == 'auth-fief'
Requires-Dist: fps-auth-jupyterhub>=0.9.4,<0.10.0 ; extra == 'auth-jupyterhub'
Requires-Dist: fps-file-watcher-poll>=0.1.4,<0.2.0 ; extra == 'file-watcher-poll'
Requires-Dist: fps-jupyterlab>=0.10.5,<0.11.0 ; extra == 'jupyterlab'
Requires-Dist: fps-kernel-web-worker>=0.1.7,<0.2.0 ; extra == 'kernel-web-worker'
Requires-Dist: fps-noauth>=0.9.4,<0.10.0 ; extra == 'noauth'
Requires-Dist: fps-notebook>=0.9.7,<0.10.0 ; extra == 'notebook'
Requires-Dist: fps-resource-usage>=0.9.4,<0.10.0 ; extra == 'resource-usage'
Requires-Dist: fps-webdav>=0.9.4,<0.10.0 ; extra == 'webdav'
Requires-Python: >=3.10
Project-URL: Homepage, https://jupyter.org
Provides-Extra: auth
Provides-Extra: auth-fief
Provides-Extra: auth-jupyterhub
Provides-Extra: file-watcher-poll
Provides-Extra: jupyterlab
Provides-Extra: kernel-web-worker
Provides-Extra: noauth
Provides-Extra: notebook
Provides-Extra: resource-usage
Provides-Extra: webdav
